kalm/__init__.py
kalm/airflow/__init__.py
kalm/airflow/airflow.py
kalm/awx/awx_common.py
kalm/awx/awx_credential.py
kalm/awx/awx_executionenvironments.py
kalm/awx/awx_hosts.py
kalm/awx/awx_organisation.py
kalm/awx/awx_project.py
kalm/awx_common.py
kalm/bump/__init__.py
kalm/bump/bump.py
kalm/common.py
kalm/dns/__init__.py
kalm/dns/cloudflare.py
kalm/dns/dns.py
kalm/gitea/__init__.py
kalm/gitea/git.py
kalm/gitea/git.save.py
kalm/inabox/__init__.py
kalm/inabox/inabox.py
kalm/inabox/virtlib.py
kalm/inthevault/__init__.py
kalm/inthevault/inthevault.py
kalm/jenkins/__init__.py
kalm/jenkins/jenkins.py
kalm/kalm.py
kalm/kalm.py.old
kalm/libvirt/__init__.py
kalm/libvirt/libvirt.py
kalm/libvirt/serve.py
kalm/netbox/__init__.py
kalm/netbox/clusters.py
kalm/netbox/common.py
kalm/netbox/netbox.py
kalm/netbox/netbox_ipaddress.py
kalm/netbox/netbox_server.py
kalm/netbox/organization.py
kalm/netbox/redis.py
kalm/netbox/serve.py
kalm/netbox/subprojects.py
kalm/netbox/terraform/cmdb/cluster_template.templ
kalm/netbox/terraform/cmdb/clustergroups.tf
kalm/netbox/terraform/cmdb/clusters.tf
kalm/netbox/terraform/cmdb/clustertypes.tf
kalm/netbox/terraform/cmdb/createtags.sh
kalm/netbox/terraform/cmdb/data/data_resource1.tf
kalm/netbox/terraform/cmdb/demoserver.tf
kalm/netbox/terraform/cmdb/deviceroles.tf
kalm/netbox/terraform/cmdb/devices.tf
kalm/netbox/terraform/cmdb/devicetypes.tf
kalm/netbox/terraform/cmdb/installprovider.sh
kalm/netbox/terraform/cmdb/inventory.json
kalm/netbox/terraform/cmdb/inventory.py
kalm/netbox/terraform/cmdb/locations.tf
kalm/netbox/terraform/cmdb/main.tf
kalm/netbox/terraform/cmdb/manufactors.tf
kalm/netbox/terraform/cmdb/modules/virtualmachine/main.tf
kalm/netbox/terraform/cmdb/modules/virtualmachine/output.tf
kalm/netbox/terraform/cmdb/modules/virtualmachine/variables.tf
kalm/netbox/terraform/cmdb/netboxinfo.py
kalm/netbox/terraform/cmdb/outputs.tf
kalm/netbox/terraform/cmdb/platforms.tf
kalm/netbox/terraform/cmdb/providers.tf
kalm-3.11.234.dist-info/LICENSE.txt
kalm-3.11.234.dist-info/METADATA
kalm-3.11.234.dist-info/WHEEL
kalm-3.11.234.dist-info/entry_points.txt
kalm-3.11.234.dist-info/RECORD
